<annotation>
  <filename>0000048.png</filename>
  <size>
    <width>720</width>
    <height>1280</height>
    <depth>3</depth>
  </size>
  <object>
    <name>vehicle</name>
    <bndbox>
      <xmin>408</xmin>
      <ymin>376</ymin>
      <xmax>551</xmax>
      <ymax>452</ymax>
    </bndbox>
  </object>
  <object>
    <name>vehicle</name>
    <bndbox>
      <xmin>226</xmin>
      <ymin>689</ymin>
      <xmax>696</xmax>
      <ymax>1012</ymax>
    </bndbox>
  </object>
  <object>
    <name>vehicle</name>
    <bndbox>
      <xmin>9</xmin>
      <ymin>587</ymin>
      <xmax>304</xmax>
      <ymax>782</ymax>
    </bndbox>
  </object>
  <object>
    <name>vehicle</name>
    <bndbox>
      <xmin>145</xmin>
      <ymin>364</ymin>
      <xmax>216</xmax>
      <ymax>411</ymax>
    </bndbox>
  </object>
  <object>
    <name>vehicle</name>
    <bndbox>
      <xmin>560</xmin>
      <ymin>398</ymin>
      <xmax>704</xmax>
      <ymax>468</ymax>
    </bndbox>
  </object>
  <object>
    <name>license_plate</name>
    <bndbox>
      <xmin>604</xmin>
      <ymin>955</ymin>
      <xmax>650</xmax>
      <ymax>986</ymax>
    </bndbox>
  </object>
  <object>
    <name>vehicle</name>
    <bndbox>
      <xmin>281</xmin>
      <ymin>544</ymin>
      <xmax>623</xmax>
      <ymax>775</ymax>
    </bndbox>
  </object>
</annotation>
