<annotation>
  <filename>0000038.png</filename>
  <size>
    <width>720</width>
    <height>1280</height>
    <depth>3</depth>
  </size>
  <object>
    <name>vehicle</name>
    <bndbox>
      <xmin>411</xmin>
      <ymin>378</ymin>
      <xmax>549</xmax>
      <ymax>451</ymax>
    </bndbox>
  </object>
  <object>
    <name>vehicle</name>
    <bndbox>
      <xmin>141</xmin>
      <ymin>368</ymin>
      <xmax>212</xmax>
      <ymax>412</ymax>
    </bndbox>
  </object>
  <object>
    <name>vehicle</name>
    <bndbox>
      <xmin>220</xmin>
      <ymin>689</ymin>
      <xmax>695</xmax>
      <ymax>1011</ymax>
    </bndbox>
  </object>
  <object>
    <name>vehicle</name>
    <bndbox>
      <xmin>8</xmin>
      <ymin>585</ymin>
      <xmax>305</xmax>
      <ymax>786</ymax>
    </bndbox>
  </object>
  <object>
    <name>vehicle</name>
    <bndbox>
      <xmin>556</xmin>
      <ymin>397</ymin>
      <xmax>713</xmax>
      <ymax>476</ymax>
    </bndbox>
  </object>
  <object>
    <name>license_plate</name>
    <bndbox>
      <xmin>603</xmin>
      <ymin>956</ymin>
      <xmax>649</xmax>
      <ymax>986</ymax>
    </bndbox>
  </object>
  <object>
    <name>vehicle</name>
    <bndbox>
      <xmin>274</xmin>
      <ymin>536</ymin>
      <xmax>629</xmax>
      <ymax>777</ymax>
    </bndbox>
  </object>
</annotation>
